{"status":"success","type":"photos","photos":[{"id":927546378,"key":"17daca556776cb705b7193bbea296927","w":5568,"g":3712,"f":false,"c":false,"l":false},{"id":927546475,"key":"aee681fa8daebec97ae29851195cf11e","w":5568,"g":3712,"f":false,"c":false,"l":false},{"id":927546613,"key":"501b9f1bc5d2f681f01b395215b9f5df","w":5568,"g":3712,"f":false,"c":false,"l":false},{"id":927546638,"key":"d20257ac8e2c9be42d71dbbb5a4edc75","w":5568,"g":3712,"f":false,"c":false,"l":false},{"id":927546768,"key":"e75fd93c9fac2072c059161058ac367b","w":5568,"g":3712,"f":false,"c":false,"l":false},{"id":927546865,"key":"93b847a780bc074f54cfc1215b8bf03d","w":5568,"g":3712,"f":false,"c":false,"l":false},{"id":927546911,"key":"256d364869ef2f2253dd6e7a4d6f9e15","w":5568,"g":3712,"f":false,"c":false,"l":false},{"id":927547096,"key":"bc86af60641b0fc9bf10315cf0203aa3","w":5568,"g":3712,"f":false,"c":false,"l":false},{"id":927547073,"key":"0ca47e50e68c48cf239896c349b048b7","w":5568,"g":3712,"f":false,"c":false,"l":false},{"id":927547269,"key":"3f672ea160724cd72d88177c81a6da91","w":5568,"g":3712,"f":false,"c":false,"l":false},{"id":927547258,"key":"a47da4721e0099b99b144a97cc9bb392","w":5568,"g":3712,"f":false,"c":false,"l":false},{"id":927547422,"key":"f28b5c7d5d0ff2ad3534e4dde84840c2","w":5568,"g":3712,"f":false,"c":false,"l":false},{"id":927547397,"key":"6bc9fc96c0c7761458e9163efba3c333","w":5568,"g":3712,"f":false,"c":false,"l":false},{"id":927547573,"key":"98f8bb43e2619d8d0e8be958d9a8358b","w":5568,"g":3712,"f":false,"c":false,"l":false},{"id":927547549,"key":"aa73a47b034bd3ca457fa8ca8e3347ce","w":5568,"g":3712,"f":false,"c":false,"l":false},{"id":927547707,"key":"835d393d34bb0b9115ee044f231f35c9","w":5568,"g":3712,"f":false,"c":false,"l":false},{"id":927547729,"key":"67e9a2c0a9bfa41a26d2ecdb8e5a210d","w":5568,"g":3712,"f":false,"c":false,"l":false},{"id":927547871,"key":"7b970fa07bc2e61a6d8aae8a36c69f0e","w":5568,"g":3712,"f":false,"c":false,"l":false},{"id":927547870,"key":"0b8b6004e9d36c829550ec587ad69f22","w":5568,"g":3712,"f":false,"c":false,"l":false},{"id":927548004,"key":"f4d2012b66796b994478baa47ccb68d8","w":5568,"g":3712,"f":false,"c":false,"l":false},{"id":927548095,"key":"d518db53786e55f5b066dcb73b960930","w":5568,"g":3712,"f":false,"c":false,"l":false},{"id":927548125,"key":"9acc4c75fc001f019c1f3eb0825f3935","w":5568,"g":3712,"f":false,"c":false,"l":false},{"id":927548270,"key":"dbd6c27adaf927517a1e5cd3791e60f5","w":5568,"g":3712,"f":false,"c":false,"l":false},{"id":927548271,"key":"2c9157ab6179a00b71247a2eb86b1c28","w":5568,"g":3712,"f":false,"c":false,"l":false},{"id":927548431,"key":"7dc7837e2a7bd1787959c21ffdc51495","w":5568,"g":3712,"f":false,"c":false,"l":false},{"id":927548400,"key":"dc7b4bd3ab4a222af9bc53ca5fb88cea","w":5568,"g":3712,"f":false,"c":false,"l":false},{"id":927548526,"key":"0d430007cfaefe54778baaedc3a88f21","w":5568,"g":3712,"f":false,"c":false,"l":false},{"id":927548571,"key":"aa413c671194f252bbe418279197390d","w":5568,"g":3712,"f":false,"c":false,"l":false},{"id":927548621,"key":"22da93c6b227d9ccaeab3f25ce607be4","w":5568,"g":3712,"f":false,"c":false,"l":false},{"id":927548697,"key":"9955290582b4308a13d0c97c8954c50e","w":5568,"g":3712,"f":false,"c":false,"l":false},{"id":927548753,"key":"54b42f8cece38ae224e4e8f20533a47e","w":5568,"g":3712,"f":false,"c":false,"l":false},{"id":927548814,"key":"3fff1ab2a9dd771d6461ea2f88f23887","w":5568,"g":3712,"f":false,"c":false,"l":false},{"id":927548852,"key":"29c900e4ab02cae5fc7428f4ad3bb8dc","w":5568,"g":3712,"f":false,"c":false,"l":false},{"id":927549006,"key":"097a47f10c5bb711376288b3fe891041","w":5568,"g":3712,"f":false,"c":false,"l":false},{"id":927549010,"key":"14f74301caf3be56a647e75a001ce630","w":5568,"g":3712,"f":false,"c":false,"l":false},{"id":927549155,"key":"5480778ae4ae921efe65ed8a2badce58","w":5568,"g":3712,"f":false,"c":false,"l":false},{"id":927549213,"key":"91015d5da239c8f559a7468f50d3676e","w":5568,"g":3712,"f":false,"c":false,"l":false},{"id":927549282,"key":"d1b26db9771dbbab5acdf94a0f95be5e","w":5568,"g":3712,"f":false,"c":false,"l":false},{"id":927549357,"key":"9bb3381c1e63c9f2d0fa6faf7d7412b6","w":5568,"g":3712,"f":false,"c":false,"l":false},{"id":927549418,"key":"2f48ac21b308fd957edfd04c140e7a73","w":5568,"g":3712,"f":false,"c":false,"l":false},{"id":927549506,"key":"114bf6c327cf910e8ecdf194c5eb9d31","w":5568,"g":3712,"f":false,"c":false,"l":false},{"id":927549539,"key":"c3e75ffef9bbdd16ad63ef149550af38","w":5568,"g":3712,"f":false,"c":false,"l":false},{"id":927549642,"key":"9e0bb5eb48d90639e97c159fca8766d5","w":5568,"g":3712,"f":false,"c":false,"l":false},{"id":927549626,"key":"e54ea48c2f5ee484139b214718ca8d25","w":5568,"g":3712,"f":false,"c":false,"l":false},{"id":927549718,"key":"a96ba665a2384bf72fd5c8f1d508558f","w":5568,"g":3712,"f":false,"c":false,"l":false},{"id":927549784,"key":"27eec8f4b05659b5f7db1dd1dc7081c1","w":5568,"g":3712,"f":false,"c":false,"l":false},{"id":927549845,"key":"3f5868f85b43a5727879315f94d3fabc","w":5568,"g":3712,"f":false,"c":false,"l":false},{"id":927549878,"key":"74992fed4524a4d77d77a7107de6c180","w":5568,"g":3712,"f":false,"c":false,"l":false},{"id":927549916,"key":"ee690a323424fb49bcad8d366fe87941","w":5568,"g":3712,"f":false,"c":false,"l":false},{"id":927550013,"key":"5c5eaff74a1bab14773d6b7f0d3b3609","w":5568,"g":3712,"f":false,"c":false,"l":false},{"id":927550017,"key":"fd01f4c3c7e08a4f51e01d672c16f76a","w":5568,"g":3712,"f":false,"c":false,"l":false},{"id":927550104,"key":"e4457525693225eb41a21f6cdba86c73","w":5568,"g":3712,"f":false,"c":false,"l":false},{"id":927550170,"key":"9c79e4f5bdac7cffff7b76616e9a24d4","w":5568,"g":3712,"f":false,"c":false,"l":false},{"id":927550230,"key":"d56ef9ece8c4e644355c3640fcef594a","w":5568,"g":3712,"f":false,"c":false,"l":false},{"id":927550281,"key":"5e0484e6973c32259e1c07cdf0b858b9","w":5568,"g":3712,"f":false,"c":false,"l":false},{"id":927550374,"key":"41afa3bdb437428737d4bb0c242bad1d","w":5568,"g":3712,"f":false,"c":false,"l":false},{"id":927550378,"key":"21263e9a0906048fa013e74cb0c12fce","w":5568,"g":3712,"f":false,"c":false,"l":false},{"id":927550489,"key":"ef6afcf8c416cbbdee5d7c324cf2d5e5","w":5568,"g":3712,"f":false,"c":false,"l":false},{"id":927550493,"key":"14dcfa012da8d2b2927ef6c450ffa33e","w":5568,"g":3712,"f":false,"c":false,"l":false},{"id":927550621,"key":"f49e543f7f6d693369b870c75bd0f8d9","w":5568,"g":3712,"f":false,"c":false,"l":false},{"id":927550661,"key":"300c200fbb15d016d28ffdc21910f5d5","w":5568,"g":3712,"f":false,"c":false,"l":false},{"id":927550781,"key":"06e238e66eac2be78fc7a774eb0505ad","w":5568,"g":3712,"f":false,"c":false,"l":false},{"id":927550788,"key":"228379c152a9141fc54d4a4fb5db397e","w":5568,"g":3712,"f":false,"c":false,"l":false},{"id":927550918,"key":"8ede37d51610d8191385f04ebdc36b58","w":5568,"g":3712,"f":false,"c":false,"l":false},{"id":927550917,"key":"c8d8c188c7485b892760bf255d03e6f0","w":5568,"g":3712,"f":false,"c":false,"l":false},{"id":927551055,"key":"517848975e01bfd85f492d33c6751422","w":5568,"g":3712,"f":false,"c":false,"l":false},{"id":927551060,"key":"7092ef1cea747fcde92256ada0d20b5c","w":5568,"g":3712,"f":false,"c":false,"l":false},{"id":927551195,"key":"688abdddbd6e309f8bf8bb153ec8bef4","w":5568,"g":3712,"f":false,"c":false,"l":false},{"id":927551200,"key":"9654071d51eba3fc4020dc74a425fecd","w":5568,"g":3712,"f":false,"c":false,"l":false},{"id":927551328,"key":"f11f923798e7e792910ec08d52204e57","w":5568,"g":3712,"f":false,"c":false,"l":false},{"id":927551330,"key":"d9348273f4f0726f9e79376f0317b213","w":5568,"g":3712,"f":false,"c":false,"l":false},{"id":927551470,"key":"3a8aafce6ac2378093c9c921b2c155c1","w":5568,"g":3712,"f":false,"c":false,"l":false},{"id":927551464,"key":"1f3d4e6361f03ca7344f7c757b08ce72","w":5568,"g":3712,"f":false,"c":false,"l":false},{"id":927551607,"key":"df9b1dacc1d2584819f360ba399222fe","w":5568,"g":3712,"f":false,"c":false,"l":false},{"id":927551605,"key":"96ba73327a11b7370ff013cd8abb5aa3","w":5568,"g":3712,"f":false,"c":false,"l":false},{"id":927551721,"key":"cb1b4c58573fb70b027c80b0e2fa0227","w":5568,"g":3712,"f":false,"c":false,"l":false},{"id":927551717,"key":"df81c6418139d9a379585c0f0e2a844e","w":5568,"g":3712,"f":false,"c":false,"l":false},{"id":927551838,"key":"5c8d034a924918214d0785e90dbe1a12","w":5568,"g":3712,"f":false,"c":false,"l":false},{"id":927551844,"key":"271f998ea268adb3ee2cac5e7dfe09ea","w":5568,"g":3712,"f":false,"c":false,"l":false},{"id":927551993,"key":"fa1809e9a41d248b1b1d589d11d7514c","w":5568,"g":3712,"f":false,"c":false,"l":false},{"id":927551989,"key":"913ff77a0fe6942996edb4424896bbfd","w":5568,"g":3712,"f":false,"c":false,"l":false},{"id":927552125,"key":"3278eecfe6190cf8d4df9ff230f5c5b8","w":5568,"g":3712,"f":false,"c":false,"l":false},{"id":927552124,"key":"1bec5bc8094509a2915bcf483315ba01","w":5568,"g":3712,"f":false,"c":false,"l":false},{"id":927552254,"key":"c44d64a185e4fcbaef9f4d57ba9cf72d","w":5568,"g":3712,"f":false,"c":false,"l":false},{"id":927552303,"key":"cc9a7617766f5ad8d70adda038134bd1","w":5568,"g":3712,"f":false,"c":false,"l":false},{"id":927552422,"key":"636641b41ad6acbba40893f393400c6e","w":5568,"g":3712,"f":false,"c":false,"l":false},{"id":927552553,"key":"b7af0908a65048a069e53f09e1454185","w":5568,"g":3712,"f":false,"c":false,"l":false},{"id":927552624,"key":"787fc8eb23fafc263943404d1b562670","w":5568,"g":3712,"f":false,"c":false,"l":false},{"id":927552701,"key":"982ee5293f7352f29f7f18b8c393c13f","w":5568,"g":3712,"f":false,"c":false,"l":false},{"id":927552797,"key":"640a7e2595289e5391b6ac154c4249df","w":5568,"g":3712,"f":false,"c":false,"l":false},{"id":927552862,"key":"e86ed33e5750325041e09d3b6d26131b","w":5568,"g":3712,"f":false,"c":false,"l":false},{"id":927553038,"key":"33c5ce74fb0496c121febf4dda3a86a2","w":5568,"g":3712,"f":false,"c":false,"l":false},{"id":927552970,"key":"c437c2f5b76bd437a1ec076f225c78bd","w":5568,"g":3712,"f":false,"c":false,"l":false},{"id":927553222,"key":"ff280698476fac06017d89fac3895ef6","w":5568,"g":3712,"f":false,"c":false,"l":false},{"id":927553310,"key":"762bddecaf328437ce52bdc1a9b5f3e3","w":5568,"g":3712,"f":false,"c":false,"l":false},{"id":927553522,"key":"671d392ceadf3c6cf29ac3d43f8822e5","w":5568,"g":3712,"f":false,"c":false,"l":false},{"id":927553321,"key":"0df99cf74ffe7d1914f1620635e41bba","w":5568,"g":3712,"f":false,"c":false,"l":false},{"id":927553450,"key":"8a58dd01f879cc4bed35976c625f097c","w":5568,"g":3712,"f":false,"c":false,"l":false},{"id":927553578,"key":"70a34c4c83312e1eca7f37c99c8e8c33","w":5568,"g":3712,"f":false,"c":false,"l":false},{"id":927553738,"key":"0c313052c5bb9a05f2c9d9c1cbd98091","w":5568,"g":3712,"f":false,"c":false,"l":false},{"id":927553722,"key":"badf477d7f890904b303af9d9b139009","w":5568,"g":3712,"f":false,"c":false,"l":false},{"id":927553919,"key":"694dd5ccb16745c8df65e2375c316c81","w":5568,"g":3712,"f":false,"c":false,"l":false},{"id":927553876,"key":"14404d2a30993617357a366e76178657","w":5568,"g":3712,"f":false,"c":false,"l":false},{"id":927554026,"key":"6ecb2635829cc97a927149216ed8355f","w":5568,"g":3712,"f":false,"c":false,"l":false},{"id":927554087,"key":"4c7e2c744fff5a1ae8be29dce0d654b3","w":5568,"g":3712,"f":false,"c":false,"l":false},{"id":927554175,"key":"ee3bd649fa3fe6b7d7c50d4a732de9b5","w":5568,"g":3712,"f":false,"c":false,"l":false},{"id":927554239,"key":"b9eadde5a956c037834225eb98969679","w":5568,"g":3712,"f":false,"c":false,"l":false},{"id":927554320,"key":"57a7a8fa447d3cd29d70b54fe54c66d7","w":5568,"g":3712,"f":false,"c":false,"l":false},{"id":927554418,"key":"d43a2530c28b7e29bb76b823dbe1dcae","w":5568,"g":3712,"f":false,"c":false,"l":false},{"id":927554449,"key":"60ccdf1d127e3039a9722bf5f9ed596f","w":5568,"g":3712,"f":false,"c":false,"l":false},{"id":927554661,"key":"e34d2b872a5e0f1d58e2b5905dd621ac","w":5568,"g":3712,"f":false,"c":false,"l":false},{"id":927554535,"key":"97891a030b41b5c34913c0fac67f3248","w":5568,"g":3712,"f":false,"c":false,"l":false},{"id":927554662,"key":"2bbc86f4ecb8a88598ba4c9bdaff5a14","w":5568,"g":3712,"f":false,"c":false,"l":false},{"id":927554834,"key":"3736809c0198a5abc704c35831ea6967","w":5568,"g":3712,"f":false,"c":false,"l":false},{"id":927554828,"key":"fd6417e19a5dc596cae605a4ef2c9654","w":5568,"g":3712,"f":false,"c":false,"l":false},{"id":927554959,"key":"6b2e9fc001247c79a8f8dd44762bdb93","w":5568,"g":3712,"f":false,"c":false,"l":false},{"id":927555025,"key":"563a2e250689bf1d67ca8bfc5c16ae2e","w":5568,"g":3712,"f":false,"c":false,"l":false},{"id":927555112,"key":"adb12f3aaba4ee9d1486557bffa5dbfd","w":5568,"g":3712,"f":false,"c":false,"l":false},{"id":927555206,"key":"ccae179fce3e44d2dfba086f55455bf9","w":5568,"g":3712,"f":false,"c":false,"l":false},{"id":927555293,"key":"23032b34a44a5d9a6202afc5f11fd5df","w":5568,"g":3712,"f":false,"c":false,"l":false},{"id":927555387,"key":"8d2c09a9bd04de268b0a61c672fcbbb3","w":5568,"g":3712,"f":false,"c":false,"l":false},{"id":927555448,"key":"dbac84cf64524c6d162810519224a8c8","w":5568,"g":3712,"f":false,"c":false,"l":false},{"id":927555577,"key":"781b3de3c0a2e39d720238e58182a05e","w":5568,"g":3712,"f":false,"c":false,"l":false},{"id":927555623,"key":"2a66de72a002532a5b179463aa539d95","w":5568,"g":3712,"f":false,"c":false,"l":false},{"id":927555826,"key":"bfb7e2340558b67a8fb522aff2ea3063","w":5568,"g":3712,"f":false,"c":false,"l":false},{"id":927555816,"key":"94b7b7c85914b09c27606adcb258f9b9","w":5568,"g":3712,"f":false,"c":false,"l":false},{"id":927556064,"key":"dcef61c5cda4f6d1891818d914c41cf8","w":5568,"g":3712,"f":false,"c":false,"l":false},{"id":927556035,"key":"d180e30d52d0b1c0530603365a440146","w":5568,"g":3712,"f":false,"c":false,"l":false},{"id":927556258,"key":"ae06893903ce0544a9062812a9a879e8","w":5568,"g":3712,"f":false,"c":false,"l":false},{"id":927556290,"key":"8961d160508374c7a8ffee24de3d869c","w":5568,"g":3712,"f":false,"c":false,"l":false},{"id":927556452,"key":"1b6e2cdf70259935289b5ef3f94fa868","w":5568,"g":3712,"f":false,"c":false,"l":false},{"id":927556454,"key":"a17f82429c3cc29ca30355e4ac480f60","w":5568,"g":3712,"f":false,"c":false,"l":false},{"id":927556640,"key":"974fcf9abf7f2e8c86b81f8f973856e4","w":5568,"g":3712,"f":false,"c":false,"l":false},{"id":927556629,"key":"023a9a360a4a62f2ede63113654368b6","w":5568,"g":3712,"f":false,"c":false,"l":false},{"id":927556816,"key":"4367e8107096f68f9bb9dbccdaaa528c","w":5568,"g":3712,"f":false,"c":false,"l":false},{"id":927556788,"key":"a84cb6af7cb5efe2994ae3f34dc61b98","w":5568,"g":3712,"f":false,"c":false,"l":false},{"id":927556981,"key":"b7e613f32d28bc83dc825ff145fc9939","w":5568,"g":3712,"f":false,"c":false,"l":false},{"id":927556993,"key":"ead4a6c5ae9adcdf1dfb07a69304e203","w":5568,"g":3712,"f":false,"c":false,"l":false},{"id":927557180,"key":"ed014aa3011084518cae3d47df63ae3d","w":5568,"g":3712,"f":false,"c":false,"l":false},{"id":927557182,"key":"65a66f9b3c8b4639b87160b6eefd51de","w":5568,"g":3712,"f":false,"c":false,"l":false},{"id":927557352,"key":"4c6d1007d17b1fc72fdeab04553660f5","w":5568,"g":3712,"f":false,"c":false,"l":false},{"id":927557353,"key":"c199187fb3145d17bdb717b0268341de","w":5568,"g":3712,"f":false,"c":false,"l":false},{"id":927557524,"key":"2963052360846df55d04264e297ce12f","w":5568,"g":3712,"f":false,"c":false,"l":false},{"id":927557474,"key":"419f223dce1cd2f7f9c74cb84c7530ae","w":5568,"g":3712,"f":false,"c":false,"l":false},{"id":927557615,"key":"0d6261e1fa78a3847acb3b6f0e0789e3","w":5568,"g":3712,"f":false,"c":false,"l":false},{"id":927557655,"key":"a934e91c0c19707e8e39f455b170d2fa","w":5568,"g":3712,"f":false,"c":false,"l":false},{"id":927557805,"key":"b6500ee38390f0387274f1973a203993","w":5568,"g":3712,"f":false,"c":false,"l":false},{"id":927557800,"key":"537c1b7da25bf41610f34f6939df6bfe","w":5568,"g":3712,"f":false,"c":false,"l":false},{"id":927557973,"key":"b27ee9601c9a66116079a7c6a1f7301d","w":5568,"g":3712,"f":false,"c":false,"l":false},{"id":927557974,"key":"7cc1df22ce940893ea65604177d9ecf1","w":5568,"g":3712,"f":false,"c":false,"l":false},{"id":927558106,"key":"e6b8172aa61ef67034c63e4b9c646ef0","w":5568,"g":3712,"f":false,"c":false,"l":false},{"id":927558185,"key":"2d33d9e7c865f7cdcfca72222804064f","w":5568,"g":3712,"f":false,"c":false,"l":false},{"id":927558253,"key":"4af7495e1c8a2a43ff2362817dfb4664","w":5568,"g":3712,"f":false,"c":false,"l":false},{"id":927558366,"key":"30de6a4d9d691140a2bb4a53decf4a27","w":5568,"g":3712,"f":false,"c":false,"l":false},{"id":927558413,"key":"444e0eb59113a9d3d39892acef623730","w":5568,"g":3712,"f":false,"c":false,"l":false},{"id":927558568,"key":"359ec1562a829d88930e6d6e444fa202","w":5568,"g":3712,"f":false,"c":false,"l":false},{"id":927558588,"key":"0be3e2a18c13f73f74b45b9b369568fe","w":5568,"g":3712,"f":false,"c":false,"l":false},{"id":927558735,"key":"8ba61acfa893d006128381cdb26c80f1","w":5568,"g":3712,"f":false,"c":false,"l":false},{"id":927558754,"key":"1dfbf3152a7210aa201160b07967f953","w":5568,"g":3712,"f":false,"c":false,"l":false},{"id":927558836,"key":"707fd9ab0d26906acf655199512e3a83","w":5568,"g":3712,"f":false,"c":false,"l":false},{"id":927558907,"key":"598f12d522088af6b6ac5efdb9aff077","w":5568,"g":3712,"f":false,"c":false,"l":false},{"id":927558979,"key":"927d85e8e04b43814e73c2f49067dbff","w":5568,"g":3712,"f":false,"c":false,"l":false},{"id":927559071,"key":"05fc7a4325e857d72a5c1a7ae0f627ca","w":5568,"g":3712,"f":false,"c":false,"l":false},{"id":927559087,"key":"890d7ec1a8b09210ef107297a9843b6a","w":5568,"g":3712,"f":false,"c":false,"l":false},{"id":927559213,"key":"6dadc525d0e60177aab3ace313f56512","w":5568,"g":3712,"f":false,"c":false,"l":false},{"id":927559218,"key":"554a1e9e28598ebd51eaed9ade9cc7cf","w":5568,"g":3712,"f":false,"c":false,"l":false},{"id":927559349,"key":"1f40ee46b691c9fcca021ddc8305d246","w":5568,"g":3712,"f":false,"c":false,"l":false},{"id":927559423,"key":"5d0f4f97e9222e57c2e41a6d511d1f52","w":5568,"g":3712,"f":false,"c":false,"l":false},{"id":927559493,"key":"eafe02b21fdabf0fef7cc071fc523574","w":5568,"g":3712,"f":false,"c":false,"l":false},{"id":927559566,"key":"ff7f73ed29e9f4aa92a8ecad4b35e389","w":5568,"g":3712,"f":false,"c":false,"l":false},{"id":927559709,"key":"d5672f0327a77cbb0066d1e29daf0376","w":5568,"g":3712,"f":false,"c":false,"l":false},{"id":927559728,"key":"a475706c385fa581885d0ddfa36f2b92","w":5568,"g":3712,"f":false,"c":false,"l":false},{"id":927559894,"key":"4ab0a479ee6cb008c44eb1c36297e041","w":5568,"g":3712,"f":false,"c":false,"l":false},{"id":927559880,"key":"1e56058dc5a9815dc53d64de32f95cf4","w":5568,"g":3712,"f":false,"c":false,"l":false},{"id":927560103,"key":"c177ca21efd0b8828fc295133c9f792d","w":5568,"g":3712,"f":false,"c":false,"l":false},{"id":927560004,"key":"e0f5e5c5fade931efe662d710cfe21ec","w":5568,"g":3712,"f":false,"c":false,"l":false},{"id":927560220,"key":"2c5ee3f70dcf11d1515a1a37fecc1515","w":5568,"g":3712,"f":false,"c":false,"l":false},{"id":927560202,"key":"33a0428e678b26a242fc50975c9bfd5e","w":5568,"g":3712,"f":false,"c":false,"l":false},{"id":927560365,"key":"2a0ba30868671c104d061cf9b7245f97","w":5568,"g":3712,"f":false,"c":false,"l":false},{"id":927560325,"key":"6c05381eb0c3fc7ed3a11c97c7fbbd18","w":5568,"g":3712,"f":false,"c":false,"l":false},{"id":927560538,"key":"d379ed8bccd4107da31aa5f7d5f90aa6","w":5568,"g":3712,"f":false,"c":false,"l":false},{"id":927560528,"key":"85a5e66e3456952cb45084886e0f0ef8","w":5568,"g":3712,"f":false,"c":false,"l":false},{"id":927560700,"key":"e4e42f3ad7aeef0386e7bc712631bbd0","w":5568,"g":3712,"f":false,"c":false,"l":false},{"id":927560696,"key":"2e4c45d607cb3d12836247ab11ac2bc2","w":5568,"g":3712,"f":false,"c":false,"l":false},{"id":927560881,"key":"99f75a3fbbf2e40d23b728e037f0a94f","w":5568,"g":3712,"f":false,"c":false,"l":false},{"id":927560878,"key":"f3dc53ea8439ca72e25abd5c6219d849","w":5568,"g":3712,"f":false,"c":false,"l":false},{"id":927561003,"key":"2358b7dffe79e902a0a215eeb5bc1b7e","w":5568,"g":3712,"f":false,"c":false,"l":false},{"id":927561081,"key":"98b5144f5992df215cb653207a80c6aa","w":5568,"g":3712,"f":false,"c":false,"l":false},{"id":927561175,"key":"08d6b0bb4398c5730f745f1081675057","w":5568,"g":3712,"f":false,"c":false,"l":false},{"id":927561214,"key":"d5cb802176b346439dec114af8fa8908","w":5568,"g":3712,"f":false,"c":false,"l":false},{"id":927561376,"key":"a28d03a690e172a642e43860e67f0837","w":5568,"g":3712,"f":false,"c":false,"l":false},{"id":927561301,"key":"4ee4d78f8b60b76ef5ba434102bd7e36","w":5568,"g":3712,"f":false,"c":false,"l":false},{"id":927561475,"key":"00246e04101aea411d89632cff9dfe79","w":5568,"g":3712,"f":false,"c":false,"l":false},{"id":927561578,"key":"a5e00e7081401ee8628145df27836434","w":5568,"g":3712,"f":false,"c":false,"l":false},{"id":927561705,"key":"2292415b02289d947929896a702ec660","w":5568,"g":3712,"f":false,"c":false,"l":false},{"id":927561567,"key":"a4fc1c9c7d649703f84aacb425ac796b","w":5568,"g":3712,"f":false,"c":false,"l":false},{"id":927561700,"key":"dca57289c3c8c1fa48958b0842f205f5","w":5568,"g":3712,"f":false,"c":false,"l":false},{"id":927561917,"key":"d387d41a415d21f5424f6ee281db10fa","w":5568,"g":3712,"f":false,"c":false,"l":false},{"id":927561844,"key":"cdbc82abc63723a3290b2062e86592a1","w":5568,"g":3712,"f":false,"c":false,"l":false},{"id":927561992,"key":"81c5d31060596e386b8a380044a0f919","w":5568,"g":3712,"f":false,"c":false,"l":false},{"id":927562015,"key":"0f0d14641ddcbffab76833713cb545ac","w":5568,"g":3712,"f":false,"c":false,"l":false},{"id":927562196,"key":"8764d5a857701ea8ad9b311b2c9a95c5","w":5568,"g":3712,"f":false,"c":false,"l":false},{"id":927562138,"key":"5f3792432ce56452ef939a5071076552","w":5568,"g":3712,"f":false,"c":false,"l":false},{"id":927562326,"key":"4c9b0c015364b592ba3277d1402a1c01","w":5568,"g":3712,"f":false,"c":false,"l":false},{"id":927562323,"key":"cf660526c7db6a6d4b3e21a4f773e597","w":5568,"g":3712,"f":false,"c":false,"l":false},{"id":927562491,"key":"ddbce28f7de732f2274a43ad1e2a9c60","w":5568,"g":3712,"f":false,"c":false,"l":false},{"id":927562504,"key":"179db2a1ac894ad70a51034deb058c61","w":5568,"g":3712,"f":false,"c":false,"l":false},{"id":927562673,"key":"8b4c9dacf9dbac9b9224c19fec55d784","w":5568,"g":3712,"f":false,"c":false,"l":false},{"id":927562584,"key":"625bb60630d3a251a87fbeb010cf05f8","w":5568,"g":3712,"f":false,"c":false,"l":false},{"id":927562786,"key":"1542de92182e2d74254d9eba882a93df","w":5568,"g":3712,"f":false,"c":false,"l":false},{"id":927562847,"key":"40fa3bafd6a5d0d1d5794f1a4298873b","w":5568,"g":3712,"f":false,"c":false,"l":false},{"id":927562966,"key":"ecdef58c693998391b7c3a2cdd06a4e2","w":5568,"g":3712,"f":false,"c":false,"l":false},{"id":927562987,"key":"eef81e2d68391ef808693b2449e7b5d1","w":5568,"g":3712,"f":false,"c":false,"l":false},{"id":927563178,"key":"8507aa25d0f78ea5cbcb33f3987288fe","w":5568,"g":3712,"f":false,"c":false,"l":false},{"id":927563102,"key":"8d24b491c998db7853db977517c49434","w":5568,"g":3712,"f":false,"c":false,"l":false},{"id":927563261,"key":"6c588218b67b1054776b1cf7ea441b1f","w":5568,"g":3712,"f":false,"c":false,"l":false},{"id":927563340,"key":"00887bb9d8554af2ebd6b7ceb4598627","w":5568,"g":3712,"f":false,"c":false,"l":false},{"id":927563449,"key":"c9f2e9eca5b1cca8ee49f7db34802857","w":5568,"g":3712,"f":false,"c":false,"l":false},{"id":927563506,"key":"29efc3b4b93b48042580e960a7ecacef","w":5568,"g":3712,"f":false,"c":false,"l":false},{"id":927563721,"key":"676e1e7b6684176bcd40da08dc53266c","w":5568,"g":3712,"f":false,"c":false,"l":false},{"id":927563639,"key":"3f2600ae10a76da3c05fcc109ba19698","w":5568,"g":3712,"f":false,"c":false,"l":false},{"id":927563856,"key":"7d813033aff34452667a53e64653649b","w":5568,"g":3712,"f":false,"c":false,"l":false},{"id":927563825,"key":"7e2b4b0894284e4559d1e76d62325f17","w":5568,"g":3712,"f":false,"c":false,"l":false},{"id":927564038,"key":"5c135605451822603bd39bce412228d4","w":5568,"g":3712,"f":false,"c":false,"l":false},{"id":927564040,"key":"40e57087968a62e9e4eb0f0fb79580e4","w":5568,"g":3712,"f":false,"c":false,"l":false},{"id":927564203,"key":"353cb9ffe10218e1920c4b3362be98b0","w":5568,"g":3712,"f":false,"c":false,"l":false},{"id":927564205,"key":"6c94da1a870d229abc76854d794356b6","w":5568,"g":3712,"f":false,"c":false,"l":false},{"id":927564475,"key":"385c792439167e1aea343e1ec2fcd8b9","w":5568,"g":3712,"f":false,"c":false,"l":false},{"id":927564373,"key":"a04f78d049eb09e6d7ffe3149ab780cc","w":5568,"g":3712,"f":false,"c":false,"l":false},{"id":927564631,"key":"0b628de97fb9e935a2556cb5e1a63c11","w":5568,"g":3712,"f":false,"c":false,"l":false},{"id":927564540,"key":"fcacb4154c8347706a18ca23644033b4","w":5568,"g":3712,"f":false,"c":false,"l":false},{"id":927564742,"key":"07fc5eef0e16bfc64064d3f62cee18c4","w":5568,"g":3712,"f":false,"c":false,"l":false},{"id":927564821,"key":"1a6a238ce9cd06987a89b2f61681234c","w":5568,"g":3712,"f":false,"c":false,"l":false},{"id":927564969,"key":"d76977e017c3bf134a481a264166ccbb","w":5568,"g":3712,"f":false,"c":false,"l":false},{"id":927564970,"key":"8e2e0f0ea476e5e72b84fcfafe056ccb","w":5568,"g":3712,"f":false,"c":false,"l":false},{"id":927565140,"key":"0674cb1468a0e12b90d519b90f872847","w":5568,"g":3712,"f":false,"c":false,"l":false},{"id":927565182,"key":"aa48b40e47d7d1552ce51eee35a5b1ef","w":5568,"g":3712,"f":false,"c":false,"l":false},{"id":927565340,"key":"9b8f0dd8be5b2c34fab113c0d55353ba","w":5568,"g":3712,"f":false,"c":false,"l":false},{"id":927565265,"key":"3127fd0442a371244bfb879d311bbc17","w":5568,"g":3712,"f":false,"c":false,"l":false},{"id":927565559,"key":"72d7a6bb7ecc48f627368da1c7f23a62","w":5568,"g":3712,"f":false,"c":false,"l":false},{"id":927565507,"key":"6ca35e14f72e04e92ba85e27bec40db8","w":5568,"g":3712,"f":false,"c":false,"l":false},{"id":927565746,"key":"56e260afb21b08fa61fc6e930404aa38","w":5568,"g":3712,"f":false,"c":false,"l":false},{"id":927565742,"key":"1202e8d961e1fde71f7d2c9c36f4f430","w":5568,"g":3712,"f":false,"c":false,"l":false},{"id":927565906,"key":"c012faa7698da5714508dc1cb4120d54","w":5568,"g":3712,"f":false,"c":false,"l":false},{"id":927565898,"key":"75911f6d01fb82087d3301ebd0c5e5a3","w":5568,"g":3712,"f":false,"c":false,"l":false},{"id":927566040,"key":"f113626f8e0853cf4082d1002a904432","w":5568,"g":3712,"f":false,"c":false,"l":false},{"id":927566099,"key":"f5ed56d801c0326216c721104b10bbca","w":5568,"g":3712,"f":false,"c":false,"l":false},{"id":927566168,"key":"626014741a120391b8b006c342b1ba2f","w":5568,"g":3712,"f":false,"c":false,"l":false},{"id":927566299,"key":"43b1014c26f6cb1ffe86bdfa0d06ee18","w":5568,"g":3712,"f":false,"c":false,"l":false},{"id":927566357,"key":"c76fcfaeb653a9863f8f159117c37daf","w":5568,"g":3712,"f":false,"c":false,"l":false},{"id":927566482,"key":"b017a79ad8ae2ae55de3f12621a1e307","w":5568,"g":3712,"f":false,"c":false,"l":false},{"id":927566461,"key":"41f2beabcbec0cb662dd2185be4fed99","w":5568,"g":3712,"f":false,"c":false,"l":false},{"id":927566614,"key":"3fbcb10a46da717e8620cbf9ad58baae","w":5568,"g":3712,"f":false,"c":false,"l":false},{"id":927566618,"key":"66b0743180c67ef0d8ce316fab4e09f4","w":5568,"g":3712,"f":false,"c":false,"l":false},{"id":927566805,"key":"21fe4a7d9eac25ab8af7b5f54cf123c8","w":5568,"g":3712,"f":false,"c":false,"l":false},{"id":927566739,"key":"bfc75bcbd34cd40bead51f367fa32b17","w":5568,"g":3712,"f":false,"c":false,"l":false},{"id":927566939,"key":"1fd6c49ad05430d6a0a0ee64667af2d7","w":5568,"g":3712,"f":false,"c":false,"l":false},{"id":927566866,"key":"03cdc101dd84ac8360416cb3bf6386ab","w":5568,"g":3712,"f":false,"c":false,"l":false},{"id":927566977,"key":"6c2ec1d4c4a776ed470529ad5287d9d1","w":5568,"g":3712,"f":false,"c":false,"l":false},{"id":927567103,"key":"08f121dc766ed80f2ae497bd87b1a252","w":5568,"g":3712,"f":false,"c":false,"l":false},{"id":927567035,"key":"70a1010eed16dd620f2af220061ebe42","w":5568,"g":3712,"f":false,"c":false,"l":false},{"id":927567140,"key":"48f14e392778267fb26b477c05d9b238","w":5568,"g":3712,"f":false,"c":false,"l":false},{"id":927567226,"key":"abb841d6b5f602eebc3f0fd030f1a86d","w":5568,"g":3712,"f":false,"c":false,"l":false},{"id":927567260,"key":"dbd2b8fc6154f2aa69128740d5fdd3c8","w":5568,"g":3712,"f":false,"c":false,"l":false},{"id":927567392,"key":"680fdb095ce86466c88a53e246161819","w":5568,"g":3712,"f":false,"c":false,"l":false},{"id":927567340,"key":"3f6e826c03075d6365fcdfefd227ef72","w":5568,"g":3712,"f":false,"c":false,"l":false},{"id":927567474,"key":"6715bb314e4c21fa54ac57961d36757b","w":5568,"g":3712,"f":false,"c":false,"l":false},{"id":927567483,"key":"af7b41ddc7d6eeb1443ecc7116edc1cd","w":5568,"g":3712,"f":false,"c":false,"l":false},{"id":927567634,"key":"68e289b99694943fa16fe4c9d4607b9e","w":5568,"g":3712,"f":false,"c":false,"l":false},{"id":927567549,"key":"98c6da0ef896e3b564e04225cd850d4e","w":5568,"g":3712,"f":false,"c":false,"l":false},{"id":927567641,"key":"2ed1a1cbc12a7cb0c2639485cc412138","w":5568,"g":3712,"f":false,"c":false,"l":false},{"id":927567750,"key":"b19e9bdb7e3d4c87faa11075dcec827b","w":5568,"g":3712,"f":false,"c":false,"l":false},{"id":927567746,"key":"08aa38011ddfe74a578a6d7a477cb0c8","w":5568,"g":3712,"f":false,"c":false,"l":false},{"id":927567841,"key":"2358ba80bd125045bafeb5ccee63e827","w":5568,"g":3712,"f":false,"c":false,"l":false},{"id":927567846,"key":"23a5a596cd6484bff7af88bdedb4a41a","w":5568,"g":3712,"f":false,"c":false,"l":false},{"id":927567944,"key":"71496fed16a1217a699d010f74ed176d","w":5568,"g":3712,"f":false,"c":false,"l":false},{"id":927567945,"key":"77bc420a3737ab79a73a2bc1b5314566","w":5568,"g":3712,"f":false,"c":false,"l":false},{"id":927568046,"key":"2b63d6cf6c4494e57147441ca1729af3","w":5568,"g":3712,"f":false,"c":false,"l":false},{"id":927568053,"key":"552cce4ee43795bf4f37f185d60f0e30","w":5568,"g":3712,"f":false,"c":false,"l":false},{"id":927568115,"key":"f3260bea8073b46814aa51b52a1322b3","w":5568,"g":3712,"f":false,"c":false,"l":false},{"id":927568182,"key":"42890beb16e2ce62eba6f96136326ddb","w":5568,"g":3712,"f":false,"c":false,"l":false},{"id":927568227,"key":"5ebca5abdeb0b6e4e9bb16463b47b451","w":5568,"g":3712,"f":false,"c":false,"l":false},{"id":927568340,"key":"2cdd254df607b2338f0ea518fc171274","w":5568,"g":3712,"f":false,"c":false,"l":false},{"id":927568325,"key":"d72271c29da9526fd73b946401016c94","w":5568,"g":3712,"f":false,"c":false,"l":false},{"id":927568457,"key":"404c369169d033f69def71bd5d3b8168","w":5568,"g":3712,"f":false,"c":false,"l":false},{"id":927568460,"key":"2ff0336954f7a45d9dfb127b4cefb177","w":5568,"g":3712,"f":false,"c":false,"l":false},{"id":927568549,"key":"2bf3721d92906284d0bc0c54f5a71890","w":5568,"g":3712,"f":false,"c":false,"l":false},{"id":927568592,"key":"c8bc42508fa73175381168e6c76d0e67","w":5568,"g":3712,"f":false,"c":false,"l":false},{"id":927568634,"key":"86c48172a45d430c04c172564473d971","w":5568,"g":3712,"f":false,"c":false,"l":false},{"id":927568704,"key":"7daef7065794ff7b424d9c3f0dcc1af9","w":5568,"g":3712,"f":false,"c":false,"l":false},{"id":927568739,"key":"e53076e683d12f338ed240cca07f81c3","w":5568,"g":3712,"f":false,"c":false,"l":false},{"id":927568801,"key":"b394f6eb093accbf405c4ea8d4b9c83f","w":5568,"g":3712,"f":false,"c":false,"l":false},{"id":927568871,"key":"3a34548bf436b2146d820f6ad70b9d1c","w":5568,"g":3712,"f":false,"c":false,"l":false},{"id":927568912,"key":"6a897681df2de84b7ebaaa8f5e5f268d","w":5568,"g":3712,"f":false,"c":false,"l":false},{"id":927568979,"key":"cd3140fdeb66496674c1be6ffa636899","w":5568,"g":3712,"f":false,"c":false,"l":false},{"id":927568988,"key":"d213df077b48ae0d9cd9510c17747328","w":5568,"g":3712,"f":false,"c":false,"l":false},{"id":927569063,"key":"6fae4edb705d26c6b5f142fb8c7ec1c5","w":5568,"g":3712,"f":false,"c":false,"l":false},{"id":927569102,"key":"c0732913c1f3bb3ce0f76719d6921ea9","w":5568,"g":3712,"f":false,"c":false,"l":false},{"id":927569168,"key":"da3890d5801814a6524794ed08e93c1b","w":5568,"g":3712,"f":false,"c":false,"l":false},{"id":927569213,"key":"f3927d167c10ee24b406e62488838912","w":5568,"g":3712,"f":false,"c":false,"l":false},{"id":927569258,"key":"8004eb01918f8b0a0dd57f9b58144498","w":5568,"g":3712,"f":false,"c":false,"l":false},{"id":927569328,"key":"8b78d315150e8d6d4fda66729527aa36","w":5568,"g":3712,"f":false,"c":false,"l":false},{"id":927569373,"key":"71167d91810ebcc8a461c954d5b65157","w":5568,"g":3712,"f":false,"c":false,"l":false},{"id":927569415,"key":"91fcaea123fce37a0bdb0525473d2410","w":5568,"g":3712,"f":false,"c":false,"l":false},{"id":927569478,"key":"fff291336e2c453c5ee6d89eb344fa39","w":5568,"g":3712,"f":false,"c":false,"l":false},{"id":927569507,"key":"b228572a97db888cc00bd5d41ed81fd7","w":5568,"g":3712,"f":false,"c":false,"l":false},{"id":927569567,"key":"b36ec2ff1a4f353055ff191ca504a2f3","w":5568,"g":3712,"f":false,"c":false,"l":false},{"id":927569593,"key":"be45556c90b39d6a991b1fc2e1dad236","w":5568,"g":3712,"f":false,"c":false,"l":false},{"id":927569708,"key":"af33bdc20835cde513b83b182288649a","w":5568,"g":3712,"f":false,"c":false,"l":false},{"id":927569642,"key":"e34aaeef57814fda19f67c676a9b1f56","w":5568,"g":3712,"f":false,"c":false,"l":false},{"id":927569747,"key":"951932e3bb190cc1b28498640f07bcc7","w":5568,"g":3712,"f":false,"c":false,"l":false},{"id":927569830,"key":"bebfed69b4130f5475ae37ec4a0ebef4","w":5568,"g":3712,"f":false,"c":false,"l":false},{"id":927569802,"key":"842d5e801b42c0afd598b642c3b399cb","w":5568,"g":3712,"f":false,"c":false,"l":false},{"id":927569870,"key":"9a5f2ae38872c4c1f98ac41dcdd328c7","w":5568,"g":3712,"f":false,"c":false,"l":false},{"id":927569947,"key":"9f208527a832e4ca41730bc7fa11c4d6","w":5568,"g":3712,"f":false,"c":false,"l":false},{"id":927569956,"key":"6dbf56887b14730bbcbd2a30ed82c47d","w":5568,"g":3712,"f":false,"c":false,"l":false},{"id":927570039,"key":"39eae5bf413f875e85976c8f7607390a","w":5568,"g":3712,"f":false,"c":false,"l":false},{"id":927570084,"key":"abafc2a37a497ba8dc12fbe6f5fc3b7b","w":5568,"g":3712,"f":false,"c":false,"l":false},{"id":927570203,"key":"e0403b8d9d175fb9359e49a8f8120039","w":5568,"g":3712,"f":false,"c":false,"l":false},{"id":927570138,"key":"1d9ff4db2101499f9f3b01f4ec070260","w":5568,"g":3712,"f":false,"c":false,"l":false},{"id":927570236,"key":"210ca33c1555725a7792a412096ac316","w":5568,"g":3712,"f":false,"c":false,"l":false},{"id":927570296,"key":"75584c1c5ff1888e79eb1ce9094cea91","w":5568,"g":3712,"f":false,"c":false,"l":false},{"id":927570397,"key":"bfcf33d0c1ce1d9e527cfdef7e0016e4","w":5568,"g":3712,"f":false,"c":false,"l":false},{"id":927570456,"key":"d5599d10457f7bb034d8a1d30725b4be","w":5568,"g":3712,"f":false,"c":false,"l":false},{"id":927570398,"key":"28bcd3a76b903411a148a34447d9a0fa","w":5568,"g":3712,"f":false,"c":false,"l":false},{"id":927570511,"key":"c29d69bd45290aaaec81d28b0be95b65","w":5568,"g":3712,"f":false,"c":false,"l":false},{"id":927570562,"key":"5a8c43176f53416f4bb825a1f1c98e33","w":5568,"g":3712,"f":false,"c":false,"l":false},{"id":927570612,"key":"2b4022393628ab1f60b4e9624e7e9044","w":5568,"g":3712,"f":false,"c":false,"l":false},{"id":927570671,"key":"dbc9f95ee7deefb78368a797b938bc71","w":5568,"g":3712,"f":false,"c":false,"l":false},{"id":927570687,"key":"95c6856506dee69444f39c4e5ba92610","w":5568,"g":3712,"f":false,"c":false,"l":false},{"id":927570787,"key":"c9ae234c61264aa61074881c1ab8ec20","w":5568,"g":3712,"f":false,"c":false,"l":false},{"id":927570768,"key":"3ee2c1dc3550cc02ba21eb90dfc86f0d","w":5568,"g":3712,"f":false,"c":false,"l":false},{"id":927570917,"key":"34d05fda3b0a926c69643eae382aadee","w":5568,"g":3712,"f":false,"c":false,"l":false},{"id":927570857,"key":"0d006f8125a3c38c2e88c148e3a3553a","w":5568,"g":3712,"f":false,"c":false,"l":false},{"id":927570997,"key":"a8c128d514f3f44a545f1cfb64244161","w":5568,"g":3712,"f":false,"c":false,"l":false},{"id":927571117,"key":"04f0a1798895c7c4b9f49d6ba4382d2a","w":5568,"g":3712,"f":false,"c":false,"l":false},{"id":927571040,"key":"071b3a42e92ffaf149769c296910e31b","w":5568,"g":3712,"f":false,"c":false,"l":false},{"id":927571120,"key":"e634385f2d8d22dacb47f64378af1b20","w":5568,"g":3712,"f":false,"c":false,"l":false},{"id":927571242,"key":"77c1cb002433873724fd3105d1ce7f35","w":5568,"g":3712,"f":false,"c":false,"l":false},{"id":927571244,"key":"56d1fa4c0bfa88337e6aaff1602b9da9","w":5568,"g":3712,"f":false,"c":false,"l":false},{"id":927571336,"key":"c5c618c2c4551c131bcbc993bbba6718","w":5568,"g":3712,"f":false,"c":false,"l":false},{"id":927571333,"key":"502feb2a4216901a937313131297b3e7","w":5568,"g":3712,"f":false,"c":false,"l":false},{"id":927571421,"key":"99ca8e3d6c08ec0fb98132afe1b79cee","w":5568,"g":3712,"f":false,"c":false,"l":false},{"id":927571449,"key":"0f8648c10dbbac574e33e72f52db2020","w":5568,"g":3712,"f":false,"c":false,"l":false},{"id":927571514,"key":"f952d09eea768d1ff8c7a4ad55489bc2","w":5568,"g":3712,"f":false,"c":false,"l":false},{"id":927571531,"key":"64eef2c2db4047e480fafa3768a7a1d4","w":5568,"g":3712,"f":false,"c":false,"l":false},{"id":927571652,"key":"babde4adeb2cf6aaec9429bae56dc9d0","w":5568,"g":3712,"f":false,"c":false,"l":false},{"id":927571581,"key":"898da09a561f2cdbb0eedbc6eb247a42","w":5568,"g":3712,"f":false,"c":false,"l":false},{"id":927571648,"key":"10498d2567a1fe3bb50cda1cc8ddc752","w":5568,"g":3712,"f":false,"c":false,"l":false},{"id":927571754,"key":"d799d26066e83a89f90f5a06640fd39f","w":5568,"g":3712,"f":false,"c":false,"l":false},{"id":927571714,"key":"d8d21592b7ef0e1347514f26a9f6ca65","w":5568,"g":3712,"f":false,"c":false,"l":false},{"id":927571861,"key":"317f2643d918ceb36fbb20d8a1d0cb01","w":5568,"g":3712,"f":false,"c":false,"l":false},{"id":927571801,"key":"2d677b054f004a0652e76661060ab3f3","w":5568,"g":3712,"f":false,"c":false,"l":false},{"id":927571952,"key":"624979ed64987cca1b61a3973803a6ca","w":5568,"g":3712,"f":false,"c":false,"l":false},{"id":927571970,"key":"855272d9662ced435b6c0213f584a74c","w":5568,"g":3712,"f":false,"c":false,"l":false},{"id":927572041,"key":"2105f8b4f44498242351c3189363df60","w":5568,"g":3712,"f":false,"c":false,"l":false},{"id":927572080,"key":"4f491395701c0d9a85440003dea3735d","w":5568,"g":3712,"f":false,"c":false,"l":false},{"id":927572182,"key":"6812f276c76219efa2c7487fcbc72209","w":5568,"g":3712,"f":false,"c":false,"l":false},{"id":927572115,"key":"109e2f442189bb0f6a877b8f9f2bddde","w":5568,"g":3712,"f":false,"c":false,"l":false},{"id":927572268,"key":"4c1f49fd961fd897c11ff8bd9b28d237","w":5568,"g":3712,"f":false,"c":false,"l":false},{"id":927572331,"key":"e6be83b525f59b20ee3eb2716029c643","w":5568,"g":3712,"f":false,"c":false,"l":false},{"id":927572254,"key":"afe7039a2774770132b91be763d67121","w":5568,"g":3712,"f":false,"c":false,"l":false},{"id":927572352,"key":"8a442e6b5cc680b82f8a3c0779f83177","w":5568,"g":3712,"f":false,"c":false,"l":false},{"id":927572456,"key":"64aae5be9efc0d862d6b07faaffae546","w":5568,"g":3712,"f":false,"c":false,"l":false},{"id":927572451,"key":"daab19a138fb056bb2bf3a76f4f63bd5","w":5568,"g":3712,"f":false,"c":false,"l":false},{"id":927572541,"key":"f4c985dc0fd6d817583652f51100d1de","w":5568,"g":3712,"f":false,"c":false,"l":false},{"id":927572637,"key":"8836568e0be8d9324479edf67c8c0b07","w":5568,"g":3712,"f":false,"c":false,"l":false},{"id":927572691,"key":"49eb692bfd11aebf939224c574f51a3e","w":5568,"g":3712,"f":false,"c":false,"l":false},{"id":927572692,"key":"f5bbe584415147ec3e495387e98a48b2","w":5568,"g":3712,"f":false,"c":false,"l":false},{"id":927572801,"key":"981419ca30543d614179ccf5b4ed5cd0","w":5568,"g":3712,"f":false,"c":false,"l":false},{"id":927572814,"key":"3163c63fe1a315b53c9da988a84d8037","w":5568,"g":3712,"f":false,"c":false,"l":false},{"id":927572925,"key":"2de18f4c589f2d19db29defd3e939fd3","w":5568,"g":3712,"f":false,"c":false,"l":false},{"id":927572935,"key":"e221dd00d708b2c522b3bef8c953490a","w":5568,"g":3712,"f":false,"c":false,"l":false},{"id":927573071,"key":"a50ca3ee03ced393c2b5e8f653dd6590","w":5568,"g":3712,"f":false,"c":false,"l":false},{"id":927573002,"key":"01717f74180c26f658838a58082e8f30","w":5568,"g":3712,"f":false,"c":false,"l":false},{"id":927573103,"key":"467d4ca03b7e0253a468418213dfe599","w":5568,"g":3712,"f":false,"c":false,"l":false},{"id":927573180,"key":"fa0ab100c90a7837c6f197a69cd1f65d","w":5568,"g":3712,"f":false,"c":false,"l":false},{"id":927573201,"key":"4e52f9e739092f78bc80a7b60ddb879d","w":5568,"g":3712,"f":false,"c":false,"l":false},{"id":927573331,"key":"fee1ca6168c9ec99ca637b3c7e5c4147","w":5568,"g":3712,"f":false,"c":false,"l":false},{"id":927573274,"key":"a26c32eadd0b53ff383618533ea2e7ae","w":5568,"g":3712,"f":false,"c":false,"l":false},{"id":927573393,"key":"86ebe4aeb5436f005cf566d62674f393","w":5568,"g":3712,"f":false,"c":false,"l":false},{"id":927573481,"key":"834d057fa72324f14e7b3a27adec190e","w":5568,"g":3712,"f":false,"c":false,"l":false},{"id":927573545,"key":"551421d16f90a8acc8426650a851e85c","w":5568,"g":3712,"f":false,"c":false,"l":false},{"id":927573635,"key":"9d9d6e16d94bb595ee74819b6ee0e8c2","w":5568,"g":3712,"f":false,"c":false,"l":false},{"id":927573606,"key":"173abdd6c638991f3e28328a8be98b10","w":5568,"g":3712,"f":false,"c":false,"l":false},{"id":927573728,"key":"cb0b891802f288e4c092d25d91da9145","w":5568,"g":3712,"f":false,"c":false,"l":false},{"id":927573714,"key":"7b37b04ff0b1cbf031be32e8b5828e2f","w":5568,"g":3712,"f":false,"c":false,"l":false},{"id":927573826,"key":"a35a025dc1da5f6bf9b3a730337159c4","w":5568,"g":3712,"f":false,"c":false,"l":false},{"id":927573878,"key":"1fdc80b8b480d8e52e53454df385c1d7","w":5568,"g":3712,"f":false,"c":false,"l":false},{"id":927573961,"key":"692bcc2e5ccad8e0519531e85e9261a2","w":5568,"g":3712,"f":false,"c":false,"l":false},{"id":927573964,"key":"b719bf4a6b01c81d3d860ecd79c3a76d","w":5568,"g":3712,"f":false,"c":false,"l":false},{"id":927574065,"key":"4a9410fb8b2ef96c069dd2ff83586c7f","w":5568,"g":3712,"f":false,"c":false,"l":false},{"id":927574122,"key":"12c4a799f7aa7e8e94504efa0678f665","w":5568,"g":3712,"f":false,"c":false,"l":false},{"id":927574159,"key":"e70e4fecd2c16b91b5362ef4d27f6aa6","w":5568,"g":3712,"f":false,"c":false,"l":false},{"id":927574267,"key":"50c19e9b855dce69532be38b971e2ed5","w":5568,"g":3712,"f":false,"c":false,"l":false},{"id":927574264,"key":"60a1015b6821dffc49c9ef56a2471f33","w":5568,"g":3712,"f":false,"c":false,"l":false},{"id":927574379,"key":"16af2795b94625eb21022cc86a644c4f","w":5568,"g":3712,"f":false,"c":false,"l":false},{"id":927574437,"key":"93fc939c5d8eab3b53d86e57c461900c","w":5568,"g":3712,"f":false,"c":false,"l":false},{"id":927574508,"key":"72381b396338ea6eaebc5466cd1da5f0","w":5568,"g":3712,"f":false,"c":false,"l":false},{"id":927574571,"key":"2302666fde1aca981cd81571532d28a0","w":5568,"g":3712,"f":false,"c":false,"l":false},{"id":927574662,"key":"99c9edc88a770161410c6f14c035d485","w":5568,"g":3712,"f":false,"c":false,"l":false},{"id":927574656,"key":"18fd75b799b74773ba934f914d45e33d","w":5568,"g":3712,"f":false,"c":false,"l":false},{"id":927574786,"key":"658f91f9023e8ddb82551b95bd20d15a","w":5568,"g":3712,"f":false,"c":false,"l":false},{"id":927574797,"key":"53c51fef4ef6317a45cf12d2038c96df","w":5568,"g":3712,"f":false,"c":false,"l":false},{"id":927574952,"key":"e8d18b5f43f0a95d438b1692ba920c6c","w":5568,"g":3712,"f":false,"c":false,"l":false},{"id":927574905,"key":"6a197e70d24b77c3ce61e8e191bc1992","w":5568,"g":3712,"f":false,"c":false,"l":false},{"id":927575000,"key":"dc41b1b5082f768270ad477a2b40edca","w":5568,"g":3712,"f":false,"c":false,"l":false},{"id":927575068,"key":"39b9a04b103bc2056690b2bb03c4fa70","w":5568,"g":3712,"f":false,"c":false,"l":false},{"id":927575134,"key":"948b0163eda310d5feb26be8dd973f31","w":5568,"g":3712,"f":false,"c":false,"l":false},{"id":927575175,"key":"deb8865d9c05353be3a87aee966aa373","w":5568,"g":3712,"f":false,"c":false,"l":false},{"id":927575214,"key":"964e55e020d563c008a428f505fec22f","w":5568,"g":3712,"f":false,"c":false,"l":false},{"id":927575312,"key":"a7b9f4dad0c414e723a685ec892c508b","w":5568,"g":3712,"f":false,"c":false,"l":false},{"id":927575307,"key":"4aad2c6e3d9d3b235ad8817ea050a3c3","w":5568,"g":3712,"f":false,"c":false,"l":false},{"id":927575434,"key":"77d6b34e312cf4f162e7b9eb2424406e","w":5568,"g":3712,"f":false,"c":false,"l":false},{"id":927575432,"key":"2b4f62b00d62bf703a74b463aa194199","w":5568,"g":3712,"f":false,"c":false,"l":false},{"id":927575583,"key":"480529158e2014367d3fdb4f3dd953f0","w":5568,"g":3712,"f":false,"c":false,"l":false},{"id":927575576,"key":"9858fd350a6e5bf898e18533976cafd8","w":5568,"g":3712,"f":false,"c":false,"l":false},{"id":927575697,"key":"57078a1e8486305542a2a3508584ad40","w":5568,"g":3712,"f":false,"c":false,"l":false},{"id":927575776,"key":"086352cde62fd1388f51a078db4f6b76","w":5568,"g":3712,"f":false,"c":false,"l":false},{"id":927575875,"key":"f597ac257be028bccb517e38a50cd7dc","w":5568,"g":3712,"f":false,"c":false,"l":false},{"id":927575940,"key":"a88bddb5aca800b64d709fda852e60db","w":5568,"g":3712,"f":false,"c":false,"l":false},{"id":927575967,"key":"8549df35ded9676d2c3d28ee5496ec5d","w":5568,"g":3712,"f":false,"c":false,"l":false},{"id":927576020,"key":"2f0239af6d37813b49cffa206a575df5","w":5568,"g":3712,"f":false,"c":false,"l":false},{"id":927576118,"key":"d24953ed5df0ffb83fa611785d7c6a69","w":5568,"g":3712,"f":false,"c":false,"l":false},{"id":927576171,"key":"311c4b6df9cdf1c75abbe8d159c20705","w":5568,"g":3712,"f":false,"c":false,"l":false},{"id":927576279,"key":"36cdfd124dfb2d235438733d33a9a2ec","w":5568,"g":3712,"f":false,"c":false,"l":false},{"id":927576307,"key":"68dc0461475223ff444c1fecf0cf4948","w":5568,"g":3712,"f":false,"c":false,"l":false},{"id":927576367,"key":"457fd19a297ba5db6d94193bed939a61","w":5568,"g":3712,"f":false,"c":false,"l":false},{"id":927576449,"key":"93da24df8f659c6cde636b0ad7967498","w":5568,"g":3712,"f":false,"c":false,"l":false},{"id":927576451,"key":"9796088fba5fcb9078d0c7706dc89b90","w":5568,"g":3712,"f":false,"c":false,"l":false},{"id":927576566,"key":"2d0d4beab90bf40d1e96b3640d7ea697","w":5568,"g":3712,"f":false,"c":false,"l":false},{"id":927576539,"key":"2321f859a2993c16ba8ba0d8f4ba8b5a","w":5568,"g":3712,"f":false,"c":false,"l":false},{"id":927576685,"key":"a33c925181b8124dd54acceb000f40c6","w":5568,"g":3712,"f":false,"c":false,"l":false},{"id":927576662,"key":"a9716ce1d1b07083e6a51125dfed1031","w":5568,"g":3712,"f":false,"c":false,"l":false},{"id":927576788,"key":"a39e1e2b56dc6d69a840cf8cfdc5c104","w":5568,"g":3712,"f":false,"c":false,"l":false},{"id":927576909,"key":"dad31dc1ec162b230e026acab2640dfa","w":5568,"g":3712,"f":false,"c":false,"l":false},{"id":927577006,"key":"ef4b6f1a5caa2769a95957c262617681","w":5568,"g":3712,"f":false,"c":false,"l":false},{"id":927577104,"key":"a6a7c6ee1e1dbf9252caac1bcba027bf","w":5568,"g":3712,"f":false,"c":false,"l":false},{"id":927577216,"key":"3a64d794089ffea72d1b334d342592a5","w":5568,"g":3712,"f":false,"c":false,"l":false},{"id":927577263,"key":"10fc2e39e377aa8fa44acf32886265b3","w":5568,"g":3712,"f":false,"c":false,"l":false},{"id":927577362,"key":"f4df42b73ba594465b7bd2156d61642f","w":5568,"g":3712,"f":false,"c":false,"l":false},{"id":927577359,"key":"60200ed9b1139e81ac0ac018d0e97e15","w":5568,"g":3712,"f":false,"c":false,"l":false},{"id":927577478,"key":"81e2b7f7b0c3be403d1fae862f747633","w":5568,"g":3712,"f":false,"c":false,"l":false},{"id":927577504,"key":"e3a766e743f69a362050fdfe80e7de8e","w":5568,"g":3712,"f":false,"c":false,"l":false},{"id":927577579,"key":"f42260542ff6302c9d51d4a134d77471","w":5568,"g":3712,"f":false,"c":false,"l":false},{"id":927577632,"key":"5bf4084e68626f5553074b7b2f26c927","w":5568,"g":3712,"f":false,"c":false,"l":false},{"id":927577681,"key":"81015d6b1419a195fd41b8ef9d152e99","w":5568,"g":3712,"f":false,"c":false,"l":false},{"id":927577746,"key":"dda28968464765f8761056452668c518","w":5568,"g":3712,"f":false,"c":false,"l":false},{"id":927577914,"key":"bb03e065cea1dc9fe390c6f2848ec2a0","w":5568,"g":3712,"f":false,"c":false,"l":false},{"id":927577912,"key":"79b46bc5713b923937615a124b8180b6","w":5568,"g":3712,"f":false,"c":false,"l":false},{"id":927578123,"key":"ce7eb3adfad742a1c84f2dad1f4932b0","w":5568,"g":3712,"f":false,"c":false,"l":false},{"id":927578125,"key":"53d1faf805a437d9301114acfc345958","w":5568,"g":3712,"f":false,"c":false,"l":false},{"id":927578290,"key":"a9768fc9cf8a0b089974a719904546f5","w":5568,"g":3712,"f":false,"c":false,"l":false},{"id":927578293,"key":"62d66e09ae2f2a0fa660b8abf556941e","w":5568,"g":3712,"f":false,"c":false,"l":false},{"id":927578433,"key":"b3c5c5ecf4d6f30d9138b891f359970d","w":5568,"g":3712,"f":false,"c":false,"l":false},{"id":927578537,"key":"a5d8e6945584d3bbf48372b31b883fc4","w":5568,"g":3712,"f":false,"c":false,"l":false},{"id":927578575,"key":"c1faadeae0335ca297665713530fe7ae","w":5568,"g":3712,"f":false,"c":false,"l":false},{"id":927578660,"key":"f6f6a6ad3bb9f0e7b1b827360521999b","w":5568,"g":3712,"f":false,"c":false,"l":false},{"id":927578722,"key":"f8be164394ba6dbdc03ac1bf259e13d1","w":5568,"g":3712,"f":false,"c":false,"l":false},{"id":927578784,"key":"fb5082d9acb2cdc6667b43ebdbd4cc62","w":5568,"g":3712,"f":false,"c":false,"l":false},{"id":927578854,"key":"e86bf47db3c42f877e0222168afd4b4b","w":5568,"g":3712,"f":false,"c":false,"l":false},{"id":927578899,"key":"49e8cf57b29787ffbb09edaad09f3310","w":5568,"g":3712,"f":false,"c":false,"l":false},{"id":927579026,"key":"217a4888c59ab738e34669882b8f6b2c","w":5568,"g":3712,"f":false,"c":false,"l":false},{"id":927579030,"key":"d8190192a84f624e563afa2923090f05","w":5568,"g":3712,"f":false,"c":false,"l":false},{"id":927579135,"key":"d4b2aa6c78907ec89fa95f99a351e186","w":5568,"g":3712,"f":false,"c":false,"l":false},{"id":927579197,"key":"5499f2ad005be0cdfefc81b828941d47","w":5568,"g":3712,"f":false,"c":false,"l":false},{"id":927579263,"key":"bc5b40b5915e8aecefdef6067499f17c","w":5568,"g":3712,"f":false,"c":false,"l":false},{"id":927579337,"key":"d5e27ab17e76c4062aeea7a730d805b8","w":5568,"g":3712,"f":false,"c":false,"l":false},{"id":927579383,"key":"5103cf411438036c644169b399a16e2d","w":5568,"g":3712,"f":false,"c":false,"l":false},{"id":927579480,"key":"2288094ae7cba6ff5262e0db0945dfa3","w":5568,"g":3712,"f":false,"c":false,"l":false},{"id":927579478,"key":"3eb0a1c22ca58e3bd85a8b57f8bdb01a","w":5568,"g":3712,"f":false,"c":false,"l":false},{"id":927579602,"key":"38f921c1b9558f9cac9b1b68fec0fc90","w":5568,"g":3712,"f":false,"c":false,"l":false},{"id":927579598,"key":"38e6f27645551017497e42a7d3882cf1","w":5568,"g":3712,"f":false,"c":false,"l":false},{"id":927579669,"key":"95d933ed5f523a71eba1c42b401b1073","w":5568,"g":3712,"f":false,"c":false,"l":false},{"id":927579763,"key":"8b054d7667a3a5b733df7814c1b9bc18","w":5568,"g":3712,"f":false,"c":false,"l":false},{"id":927579778,"key":"e20d6e83300dd1a7d6a9b4999f282aa5","w":5568,"g":3712,"f":false,"c":false,"l":false},{"id":927579864,"key":"c854e19bd3e52a9206d23eb574822b61","w":5568,"g":3712,"f":false,"c":false,"l":false},{"id":927579840,"key":"5006fa55a834918cf17f5e9ebdc83ea2","w":5568,"g":3712,"f":false,"c":false,"l":false},{"id":927579941,"key":"c02aa63c7f1b409d67e5a961fb2ced80","w":5568,"g":3712,"f":false,"c":false,"l":false},{"id":927579983,"key":"064afb353c83b00a90a696e1e6c57749","w":5568,"g":3712,"f":false,"c":false,"l":false},{"id":927580049,"key":"997a9ba6e09b5598b61fcb905f9af479","w":5568,"g":3712,"f":false,"c":false,"l":false},{"id":927580086,"key":"d90e0fec5e2f0bab3ce2f38f0dfe6358","w":5568,"g":3712,"f":false,"c":false,"l":false},{"id":927580147,"key":"71935bacab254413639994db022e0ab5","w":5568,"g":3712,"f":false,"c":false,"l":false},{"id":927580207,"key":"db7b624b425ede52f2beef860162b9e2","w":5568,"g":3712,"f":false,"c":false,"l":false},{"id":927580242,"key":"a66e53f7a9894eaf089455d93c686fbc","w":5568,"g":3712,"f":false,"c":false,"l":false},{"id":927580282,"key":"33bc3476fcc58214f6a6d4c306fb70fc","w":5568,"g":3712,"f":false,"c":false,"l":false}],"album":{"id":5226564,"n":"AppSec Day 3 - 04\/07\/2018","p":false,"xp":486,"xa":0,"c":{"url":"\/\/diy2dhgsjw6gb.cloudfront.net\/cp\/c46c83d1fb34be2e9732fb77cddced43\/l.jpg","width":5568,"height":3712,"thumb":false,"focalPoint":{"x":50,"y":50}},"s":false,"x":486},"userState":{"hasUserEmail":true,"hasEventPassword":true,"isEventContact":false,"isVisitorEventContact":false,"isAdminModeEnabled":false,"numFavorites":0,"numCartItems":0,"cartPreDiscountSubtotal":0,"cartPreDiscountSubtotalFormatted":"\u00a30.00","cartPostDiscountSubtotal":0,"cartPostDiscountSubtotalFormatted":"\u00a30.00","cartHasDiscounts":false}}